fresfolio/__init__.py
fresfolio/main.py
fresfolio/cli/__init__.py
fresfolio/cli/script.py
fresfolio/plotting/__init__.py
fresfolio/plotting/omiplot/__init__.py
fresfolio/renderers/__init__.py
fresfolio/renderers/html_renderer/__init__.py
fresfolio/renderers/inline_renderers/__init__.py
fresfolio/renderers/multiline_renderers/__init__.py
fresfolio/routes/__init__.py
fresfolio/routes/api/__init__.py
fresfolio/routes/core/__init__.py
fresfolio/static/css/app.css
fresfolio/static/css/fonts.css
fresfolio/static/css/katex.min.css
fresfolio/static/css/quasar.prod.css
fresfolio/static/css/fonts/KFOkCnqEu92Fr1MmgVxEIzIXKMnyrYk.woff2
fresfolio/static/css/fonts/KFOkCnqEu92Fr1MmgVxFIzIXKMnyrYk.woff2
fresfolio/static/css/fonts/KFOkCnqEu92Fr1MmgVxGIzIXKMnyrYk.woff2
fresfolio/static/css/fonts/KFOkCnqEu92Fr1MmgVxHIzIXKMnyrYk.woff2
fresfolio/static/css/fonts/KFOkCnqEu92Fr1MmgVxIIzIXKMny.woff2
fresfolio/static/css/fonts/KFOkCnqEu92Fr1MmgVxLIzIXKMnyrYk.woff2
fresfolio/static/css/fonts/KFOkCnqEu92Fr1MmgVxMIzIXKMnyrYk.woff2
fresfolio/static/css/fonts/KFOkCnqEu92Fr1MmgWxP.ttf
fresfolio/static/css/fonts/KFOlCnqEu92Fr1MmEU9fABc4AMP6lbBP.woff2
fresfolio/static/css/fonts/KFOlCnqEu92Fr1MmEU9fBBc4AMP6lQ.woff2
fresfolio/static/css/fonts/KFOlCnqEu92Fr1MmEU9fBxc4AMP6lbBP.woff2
fresfolio/static/css/fonts/KFOlCnqEu92Fr1MmEU9fCBc4AMP6lbBP.woff2
fresfolio/static/css/fonts/KFOlCnqEu92Fr1MmEU9fCRc4AMP6lbBP.woff2
fresfolio/static/css/fonts/KFOlCnqEu92Fr1MmEU9fChc4AMP6lbBP.woff2
fresfolio/static/css/fonts/KFOlCnqEu92Fr1MmEU9fCxc4AMP6lbBP.woff2
fresfolio/static/css/fonts/KFOlCnqEu92Fr1MmEU9vAw.ttf
fresfolio/static/css/fonts/KFOlCnqEu92Fr1MmSU5fABc4AMP6lbBP.woff2
fresfolio/static/css/fonts/KFOlCnqEu92Fr1MmSU5fBBc4AMP6lQ.woff2
fresfolio/static/css/fonts/KFOlCnqEu92Fr1MmSU5fBxc4AMP6lbBP.woff2
fresfolio/static/css/fonts/KFOlCnqEu92Fr1MmSU5fCBc4AMP6lbBP.woff2
fresfolio/static/css/fonts/KFOlCnqEu92Fr1MmSU5fCRc4AMP6lbBP.woff2
fresfolio/static/css/fonts/KFOlCnqEu92Fr1MmSU5fChc4AMP6lbBP.woff2
fresfolio-0.3.0.dist-info/LICENSE
fresfolio-0.3.0.dist-info/METADATA
fresfolio-0.3.0.dist-info/WHEEL
fresfolio-0.3.0.dist-info/entry_points.txt
fresfolio-0.3.0.dist-info/top_level.txt
fresfolio-0.3.0.dist-info/RECORD
