Metadata-Version: 2.1
Name: fresfolio
Version: 0.3.0
Summary: Flask and Vue3 based notebook for personal and research projects.
Home-page: https://github.com/dkioroglou/fresfolio/tree/main
Author: Dimitrios Kioroglou
Author-email: <d.kioroglou@hotmail.com>
License: GPL-3.0
Keywords: flask,notebook,research,reporting
Classifier: Development Status :: 1 - Planning
Classifier: Intended Audience :: Science/Research
Classifier: Programming Language :: Python :: 3
Classifier: Operating System :: Unix
Classifier: Operating System :: MacOS :: MacOS X
Classifier: Operating System :: Microsoft :: Windows
License-File: LICENSE
Requires-Dist: Flask>=2.0.2; python_version >= "3.8"
